somlib/__init__.py
somlib/example.py
somlib/som.py
somlib/som_numpy.py
somlib/som_tensor.py
somlib-0.0.4.dist-info/DESCRIPTION.rst
somlib-0.0.4.dist-info/METADATA
somlib-0.0.4.dist-info/RECORD
somlib-0.0.4.dist-info/WHEEL
somlib-0.0.4.dist-info/metadata.json
somlib-0.0.4.dist-info/top_level.txt
