Metadata-Version: 2.0
Name: somlib
Version: 0.0.4
Summary: This is python implementation for Kohonen Self Organizing map using numpy and tensor
Home-page: https://github.com/pankajr141/SOM
Author: Pankaj Rawat
Author-email: pankajr141@gmail.com
License: UNKNOWN
Platform: UNKNOWN
Classifier: Programming Language :: Python :: 3
Classifier: License :: OSI Approved :: MIT License
Classifier: Operating System :: OS Independent
Requires-Dist: matplotlib
Requires-Dist: numpy
Requires-Dist: pandas
Requires-Dist: scipy
Requires-Dist: tensorflow
